{
  "OVERVIEW": {
    "revenue": 32005887549.0,
    "directProfit": 5899745190.0,
    "directProfitRate": 20.28,
    "discountRate": 19.17,
    "progressRate": 31.3,
    "progressRateForecast": 95.6,
    "revenueForecast": 77565675556.0,
    "directProfitForecast": 17999511034.0,
    "directProfitRateForecast": 25.53,
    "discountRateForecast": 18.27,
    "operatingProfit": -5200512810.0,
    "operatingProfitForecast": 6899253034.0,
    "operatingProfitRate": -17.87,
    "operatingProfitRateForecast": 9.78,
    "revenuePrevious": 76645792201.0,
    "directProfitPrevious": 16707632365.0,
    "operatingProfitPrevious": 5708315720.0,
    "revenuePlan": 81333271000.0,
    "directProfitPlan": 18832717000.0,
    "directProfitRatePlan": 25.47,
    "revenueVsPlan": -4.6,
    "revenueVsPrevious": 1.2,
    "profitVsPlan": -4.4,
    "profitVsPrevious": 7.7
  }
}