[
  {
    "BRAND": "MLB",
    "SALES": 300.3,
    "DIRECT_PROFIT": 77.7,
    "OPERATING_PROFIT": 40.2,
    "ACHIEVEMENT": 104,
    "YOY_SALES": 9
  },
  {
    "BRAND": "MLB KIDS",
    "SALES": 71.5,
    "DIRECT_PROFIT": 0.9,
    "OPERATING_PROFIT": -9.9,
    "ACHIEVEMENT": 100,
    "YOY_SALES": 7
  },
  {
    "BRAND": "DISCOVERY",
    "SALES": 420.0,
    "DIRECT_PROFIT": 92.8,
    "OPERATING_PROFIT": 43.0,
    "ACHIEVEMENT": 104,
    "YOY_SALES": 6
  },
  {
    "BRAND": "DUVETICA",
    "SALES": 38.9,
    "DIRECT_PROFIT": 12.6,
    "OPERATING_PROFIT": 6.0,
    "ACHIEVEMENT": 102,
    "YOY_SALES": 67
  },
  {
    "BRAND": "SERGIO",
    "SALES": 4.0,
    "DIRECT_PROFIT": -1.2,
    "OPERATING_PROFIT": -7.1,
    "ACHIEVEMENT": 60,
    "YOY_SALES": -8
  },
  {
    "BRAND": "SUPRA",
    "SALES": 0.8,
    "DIRECT_PROFIT": -0.2,
    "OPERATING_PROFIT": -0.5,
    "ACHIEVEMENT": 32,
    "YOY_SALES": -56
  }
]